ftp_download/__init__.py
ftp_download/ensure.py
ftp_download/prefs.py
ftp_download/timings.py
ftp_download-0.1.1.dist-info/LICENSE
ftp_download-0.1.1.dist-info/METADATA
ftp_download-0.1.1.dist-info/WHEEL
ftp_download-0.1.1.dist-info/top_level.txt
ftp_download-0.1.1.dist-info/RECORD
