Metadata-Version: 2.1
Name: ftp_download
Version: 0.1.1
Summary: Easily download files from ftp servers!
Author-email: "Vitor F. Lins" <vflins@live.com>
License: MIT License
Project-URL: Repository, https://github.com/VFLins/ftp_download
Project-URL: Documentation, https://vflins.github.io/ftp_download/docs/ftp_download.html
Keywords: download,ftp
Classifier: Programming Language :: Python :: 3
Classifier: Operating System :: OS Independent
Classifier: License :: OSI Approved :: MIT License
Requires-Python: >=3.6
License-File: LICENSE
Provides-Extra: test
Requires-Dist: flake8 ==7.0.0 ; extra == 'test'
Requires-Dist: pytest ==7.4.4 ; extra == 'test'
Requires-Dist: pytest-cov ==4.1.0 ; extra == 'test'
Requires-Dist: tox ==4.12.0 ; extra == 'test'
Requires-Dist: mypy ==1.8.0 ; extra == 'test'
Requires-Dist: pdoc ==14.3.0 ; extra == 'test'
Requires-Dist: wheel ==0.42.0 ; extra == 'test'
